<?xml version="1.0" encoding="UTF-8" standalone="yes"?>
<Requests>
    <Request>
        <requestId>REQ2B2C8</requestId>
        <userName>nhat2112</userName>
        <fullName>triasdas</fullName>
        <email>qw23@gmail.com</email>
        <phone>0999999999</phone>
        <roomId>R017</roomId>
        <checkIn>2025-07-23T00:00:00</checkIn>
        <checkOut>2025-07-24T00:00:00</checkOut>
        <amount>800000.0</amount>
        <submittedAt>2025-07-22T15:54:02</submittedAt>
        <status>Đã từ chối</status>
        <Person>
            <fullName>triasdas</fullName>
            <documentType>Không có</documentType>
            <documentCode>1</documentCode>
        </Person>
        <History>
            <timestamp>2025-07-22T15:53:54</timestamp>
            <status>Gửi yêu cầu</status>
        </History>
        <History>
            <timestamp>2025-07-22T15:54:02</timestamp>
            <status>Đã từ chối</status>
        </History>
    </Request>
    <Request>
        <requestId>REQA536B</requestId>
        <userName>husky123</userName>
        <fullName>Trinh Nhu Nhat</fullName>
        <email>asd23@gmail.com</email>
        <phone>0999999999</phone>
        <roomId>R019</roomId>
        <checkIn>2025-07-23T00:00:00</checkIn>
        <checkOut>2025-07-24T00:00:00</checkOut>
        <amount>800000.0</amount>
        <submittedAt>2025-07-22T12:53:24</submittedAt>
        <status>Đã được duyệt</status>
        <Person>
            <fullName>Trinh Nhu Nhat</fullName>
            <documentType>Không có</documentType>
            <documentCode>1</documentCode>
        </Person>
        <History>
            <timestamp>2025-07-22T12:51:22</timestamp>
            <status>Gửi yêu cầu</status>
        </History>
        <History>
            <timestamp>2025-07-22T12:53:24</timestamp>
            <status>Đã được duyệt</status>
        </History>
    </Request>
    <Request>
        <requestId>REQ2CE0F</requestId>
        <userName>husky123</userName>
        <fullName>Trinh Nhu Nhat</fullName>
        <email>asd23@gmail.com</email>
        <phone>0999999999</phone>
        <roomId>R019</roomId>
        <checkIn>2025-07-23T00:00:00</checkIn>
        <checkOut>2025-07-24T00:00:00</checkOut>
        <amount>800000.0</amount>
        <submittedAt>2025-07-22T15:50:36</submittedAt>
        <status>Đã từ chối</status>
        <Person>
            <fullName>Trinh Nhu Nhat</fullName>
            <documentType>Không có</documentType>
            <documentCode>1</documentCode>
        </Person>
        <History>
            <timestamp>2025-07-22T12:50:22</timestamp>
            <status>Gửi yêu cầu</status>
        </History>
        <History>
            <timestamp>2025-07-22T15:50:36</timestamp>
            <status>Đã từ chối</status>
        </History>
    </Request>
    <Request>
        <requestId>REQ0FDD9</requestId>
        <userName>husky123</userName>
        <fullName>Trinh Nhu Nhat</fullName>
        <email>asd23@gmail.com</email>
        <phone>0999999999</phone>
        <roomId>R019</roomId>
        <checkIn>2025-07-23T00:00:00</checkIn>
        <checkOut>2025-07-24T00:00:00</checkOut>
        <amount>800000.0</amount>
        <submittedAt>2025-07-22T16:04:43</submittedAt>
        <status>Đã bị hủy</status>
        <Person>
            <fullName>Trinh Nhu Nhat</fullName>
            <documentType>Mã định danh</documentType>
            <documentCode>1</documentCode>
        </Person>
        <History>
            <timestamp>2025-07-22T12:47:55</timestamp>
            <status>Gửi yêu cầu</status>
        </History>
        <History>
            <timestamp>2025-07-22T16:03:55</timestamp>
            <status>Đã đọc</status>
        </History>
        <History>
            <timestamp>2025-07-22T16:04:04</timestamp>
            <status>Đã được duyệt</status>
        </History>
        <History>
            <timestamp>2025-07-22T16:04:23</timestamp>
            <status>Gửi yêu cầu hủy</status>
        </History>
        <History>
            <timestamp>2025-07-22T16:04:43</timestamp>
            <status>Đã bị hủy</status>
        </History>
    </Request>
    <Request>
        <requestId>REQ60DF5</requestId>
        <userName>husky123</userName>
        <fullName>Trinh Nhu Nhat</fullName>
        <email>asd23@gmail.com</email>
        <phone>0999999999</phone>
        <roomId>R020</roomId>
        <checkIn>2025-07-23T00:00:00</checkIn>
        <checkOut>2025-07-30T00:00:00</checkOut>
        <amount>800000.0</amount>
        <submittedAt>2025-07-22T12:34:35</submittedAt>
        <status>Đã bị hủy</status>
        <Person>
            <fullName>Trinh Nhu Nhat</fullName>
            <documentType>CCCD</documentType>
            <documentCode>1</documentCode>
        </Person>
        <History>
            <timestamp>2025-07-22T12:32:25</timestamp>
            <status>Gửi yêu cầu</status>
        </History>
        <History>
            <timestamp>2025-07-22T12:33:23</timestamp>
            <status>Đã được duyệt</status>
        </History>
        <History>
            <timestamp>2025-07-22T12:34:10</timestamp>
            <status>Gửi yêu cầu hủy</status>
        </History>
        <History>
            <timestamp>2025-07-22T12:34:35</timestamp>
            <status>Đã bị hủy</status>
        </History>
    </Request>
    <Request>
        <requestId>REQ71A3B</requestId>
        <userName>nhat2112</userName>
        <fullName>triasdas</fullName>
        <email>qw23@gmail.com</email>
        <phone>0999999999</phone>
        <roomId>R011</roomId>
        <checkIn>2025-07-20T00:00:00</checkIn>
        <checkOut>2025-07-21T00:00:00</checkOut>
        <amount>600000.0</amount>
        <submittedAt>2025-07-18T19:45:58</submittedAt>
        <status>Đã bị hủy</status>
        <Person/>
        <History>
            <timestamp>2025-07-18T19:45:03</timestamp>
            <status>Gửi yêu cầu</status>
        </History>
        <History>
            <timestamp>2025-07-18T19:45:16</timestamp>
            <status>Đã được duyệt</status>
        </History>
        <History>
            <timestamp>2025-07-18T19:45:47</timestamp>
            <status>Gửi yêu cầu hủy</status>
        </History>
        <History>
            <timestamp>2025-07-18T19:45:58</timestamp>
            <status>Đã bị hủy</status>
        </History>
    </Request>
    <Request>
        <requestId>REQF4D18</requestId>
        <userName>nhat2112</userName>
        <fullName>triasdas</fullName>
        <email>qw23@gmail.com</email>
        <phone>0999999999</phone>
        <roomId>R011</roomId>
        <checkIn>2025-07-20T00:00:00</checkIn>
        <checkOut>2025-07-21T00:00:00</checkOut>
        <amount>600000.0</amount>
        <submittedAt>2025-07-18T19:43:27</submittedAt>
        <status>Đã bị hủy</status>
        <Person/>
        <History>
            <timestamp>2025-07-18T19:40:19</timestamp>
            <status>Gửi yêu cầu</status>
        </History>
        <History>
            <timestamp>2025-07-18T19:42:15</timestamp>
            <status>Đã đọc</status>
        </History>
        <History>
            <timestamp>2025-07-18T19:42:37</timestamp>
            <status>Đã được duyệt</status>
        </History>
        <History>
            <timestamp>2025-07-18T19:42:48</timestamp>
            <status>Gửi yêu cầu hủy</status>
        </History>
        <History>
            <timestamp>2025-07-18T19:43:27</timestamp>
            <status>Đã bị hủy</status>
        </History>
    </Request>
    <Request>
        <requestId>REQ59A7E</requestId>
        <userName>nhat2112</userName>
        <fullName>triasdas</fullName>
        <email>qw23@gmail.com</email>
        <phone>0999999999</phone>
        <roomId>R012</roomId>
        <checkIn>2025-07-20T00:00:00</checkIn>
        <checkOut>2025-07-21T00:00:00</checkOut>
        <amount>600000.0</amount>
        <submittedAt>2025-07-18T19:39:15</submittedAt>
        <status>Đã được duyệt</status>
        <Person/>
        <History>
            <timestamp>2025-07-18T19:39:02</timestamp>
            <status>Gửi yêu cầu</status>
        </History>
        <History>
            <timestamp>2025-07-18T19:39:15</timestamp>
            <status>Đã được duyệt</status>
        </History>
    </Request>
    <Request>
        <requestId>REQ562C3</requestId>
        <userName>nhat2112</userName>
        <fullName>triasdas</fullName>
        <email>qw23@gmail.com</email>
        <phone>0999999999</phone>
        <roomId>R012</roomId>
        <checkIn>2025-07-20T00:00:00</checkIn>
        <checkOut>2025-07-21T00:00:00</checkOut>
        <amount>600000.0</amount>
        <submittedAt>2025-07-18T19:22:14</submittedAt>
        <status>Đã bị hủy</status>
        <Person/>
        <History>
            <timestamp>2025-07-18T19:21:28</timestamp>
            <status>Gửi yêu cầu</status>
        </History>
        <History>
            <timestamp>2025-07-18T19:21:37</timestamp>
            <status>Đã được duyệt</status>
        </History>
        <History>
            <timestamp>2025-07-18T19:21:56</timestamp>
            <status>Gửi yêu cầu hủy</status>
        </History>
        <History>
            <timestamp>2025-07-18T19:22:14</timestamp>
            <status>Đã bị hủy</status>
        </History>
    </Request>
    <Request>
        <requestId>REQ56BC0</requestId>
        <userName>nhat2112</userName>
        <fullName>triasdas</fullName>
        <email>qw23@gmail.com</email>
        <phone>0999999999</phone>
        <roomId>R013</roomId>
        <checkIn>2025-07-20T00:00:00</checkIn>
        <checkOut>2025-07-21T00:00:00</checkOut>
        <amount>600000.0</amount>
        <submittedAt>2025-07-18T19:20:08</submittedAt>
        <status>Đã bị hủy</status>
        <Person/>
        <History>
            <timestamp>2025-07-18T19:19:23</timestamp>
            <status>Gửi yêu cầu</status>
        </History>
        <History>
            <timestamp>2025-07-18T19:19:34</timestamp>
            <status>Đã được duyệt</status>
        </History>
        <History>
            <timestamp>2025-07-18T19:19:46</timestamp>
            <status>Gửi yêu cầu hủy</status>
        </History>
        <History>
            <timestamp>2025-07-18T19:20:08</timestamp>
            <status>Đã bị hủy</status>
        </History>
    </Request>
    <Request>
        <requestId>REQ308D3</requestId>
        <userName>nhat2112</userName>
        <fullName>triasdas</fullName>
        <email>qw23@gmail.com</email>
        <phone>0999999999</phone>
        <roomId>R013</roomId>
        <checkIn>2025-07-20T00:00:00</checkIn>
        <checkOut>2025-07-21T00:00:00</checkOut>
        <amount>600000.0</amount>
        <submittedAt>2025-07-18T19:18:20</submittedAt>
        <status>Đã bị hủy</status>
        <Person/>
        <History>
            <timestamp>2025-07-18T19:17:22</timestamp>
            <status>Gửi yêu cầu</status>
        </History>
        <History>
            <timestamp>2025-07-18T19:17:46</timestamp>
            <status>Đã đọc</status>
        </History>
        <History>
            <timestamp>2025-07-18T19:18:20</timestamp>
            <status>Đã bị hủy</status>
        </History>
    </Request>
    <Request>
        <requestId>REQF982A</requestId>
        <userName>husky123</userName>
        <fullName>Trinh Nhu Nhat</fullName>
        <email>asd23@gmail.com</email>
        <phone>0999999999</phone>
        <roomId>R013</roomId>
        <checkIn>2025-07-20T00:00:00</checkIn>
        <checkOut>2025-07-21T00:00:00</checkOut>
        <amount>600000.0</amount>
        <submittedAt>2025-07-18T19:10:35</submittedAt>
        <status>Đã bị hủy</status>
        <Person/>
        <History>
            <timestamp>2025-07-18T19:09:36</timestamp>
            <status>Gửi yêu cầu</status>
        </History>
        <History>
            <timestamp>2025-07-18T19:09:58</timestamp>
            <status>Đã được duyệt</status>
        </History>
        <History>
            <timestamp>2025-07-18T19:10:09</timestamp>
            <status>Gửi yêu cầu hủy</status>
        </History>
        <History>
            <timestamp>2025-07-18T19:10:35</timestamp>
            <status>Đã bị hủy</status>
        </History>
    </Request>
    <Request>
        <requestId>REQC69D7</requestId>
        <userName>husky123</userName>
        <fullName>Trinh Nhu Nhat</fullName>
        <email>asd23@gmail.com</email>
        <phone>0999999999</phone>
        <roomId>R014</roomId>
        <checkIn>2025-07-20T00:00:00</checkIn>
        <checkOut>2025-07-21T00:00:00</checkOut>
        <amount>600000.0</amount>
        <submittedAt>2025-07-18T19:07:41</submittedAt>
        <status>Đã bị hủy</status>
        <Person/>
        <History>
            <timestamp>2025-07-18T19:06:50</timestamp>
            <status>Gửi yêu cầu</status>
        </History>
        <History>
            <timestamp>2025-07-18T19:07:02</timestamp>
            <status>Đã được duyệt</status>
        </History>
        <History>
            <timestamp>2025-07-18T19:07:13</timestamp>
            <status>Gửi yêu cầu hủy</status>
        </History>
        <History>
            <timestamp>2025-07-18T19:07:41</timestamp>
            <status>Đã bị hủy</status>
        </History>
    </Request>
    <Request>
        <requestId>REQF3423</requestId>
        <userName>husky123</userName>
        <fullName>Trinh Nhu Nhat</fullName>
        <email>asd23@gmail.com</email>
        <phone>0999999999</phone>
        <roomId>R014</roomId>
        <checkIn>2025-07-20T00:00:00</checkIn>
        <checkOut>2025-07-21T00:00:00</checkOut>
        <amount>600000.0</amount>
        <submittedAt>2025-07-18T19:06:10</submittedAt>
        <status>Đã bị hủy</status>
        <Person/>
        <History>
            <timestamp>2025-07-18T19:05:27</timestamp>
            <status>Gửi yêu cầu</status>
        </History>
        <History>
            <timestamp>2025-07-18T19:05:48</timestamp>
            <status>Đã đọc</status>
        </History>
        <History>
            <timestamp>2025-07-18T19:06:10</timestamp>
            <status>Đã bị hủy</status>
        </History>
    </Request>
    <Request>
        <requestId>REQ1C71B</requestId>
        <userName>husky123</userName>
        <fullName>Trinh Nhu Nhat</fullName>
        <email>asd23@gmail.com</email>
        <phone>0999999999</phone>
        <roomId>R015</roomId>
        <checkIn>2025-07-19T00:00:00</checkIn>
        <checkOut>2025-07-26T00:00:00</checkOut>
        <amount>600000.0</amount>
        <submittedAt>2025-07-18T19:04:15</submittedAt>
        <status>Đã được duyệt</status>
        <Person/>
        <History>
            <timestamp>2025-07-18T19:03:51</timestamp>
            <status>Gửi yêu cầu</status>
        </History>
        <History>
            <timestamp>2025-07-18T19:04:15</timestamp>
            <status>Đã được duyệt</status>
        </History>
    </Request>
    <Request>
        <requestId>REQ44E5E</requestId>
        <userName>husky123</userName>
        <fullName>Trinh Nhu Nhat</fullName>
        <email>asd23@gmail.com</email>
        <phone>0999999999</phone>
        <roomId>R015</roomId>
        <checkIn>2025-07-19T00:00:00</checkIn>
        <checkOut>2025-07-26T00:00:00</checkOut>
        <amount>600000.0</amount>
        <submittedAt>2025-07-18T19:02:40</submittedAt>
        <status>Đã bị hủy</status>
        <Person/>
        <History>
            <timestamp>2025-07-18T18:58:33</timestamp>
            <status>Gửi yêu cầu</status>
        </History>
        <History>
            <timestamp>2025-07-18T18:58:50</timestamp>
            <status>Đã được duyệt</status>
        </History>
        <History>
            <timestamp>2025-07-18T19:02:27</timestamp>
            <status>Gửi yêu cầu hủy</status>
        </History>
        <History>
            <timestamp>2025-07-18T19:02:40</timestamp>
            <status>Đã bị hủy</status>
        </History>
    </Request>
    <Request>
        <requestId>REQCD0A8</requestId>
        <userName>husky123</userName>
        <fullName>Trinh Nhu Nhat</fullName>
        <email>asd23@gmail.com</email>
        <phone>0999999999</phone>
        <roomId>R016</roomId>
        <checkIn>2025-07-19T00:00:00</checkIn>
        <checkOut>2025-07-26T00:00:00</checkOut>
        <amount>800000.0</amount>
        <submittedAt>2025-07-18T18:57:10</submittedAt>
        <status>Đã bị hủy</status>
        <Person/>
        <History>
            <timestamp>2025-07-18T18:56:03</timestamp>
            <status>Gửi yêu cầu</status>
        </History>
        <History>
            <timestamp>2025-07-18T18:56:24</timestamp>
            <status>Đã đọc</status>
        </History>
        <History>
            <timestamp>2025-07-18T18:56:48</timestamp>
            <status>Đã được duyệt</status>
        </History>
        <History>
            <timestamp>2025-07-18T18:57:00</timestamp>
            <status>Gửi yêu cầu hủy</status>
        </History>
        <History>
            <timestamp>2025-07-18T18:57:10</timestamp>
            <status>Đã bị hủy</status>
        </History>
    </Request>
    <Request>
        <requestId>REQ5E690</requestId>
        <userName>husky123</userName>
        <fullName>Trinh Nhu Nhat</fullName>
        <email>asd23@gmail.com</email>
        <phone>0999999999</phone>
        <roomId>R017</roomId>
        <checkIn>2025-07-19T00:00:00</checkIn>
        <checkOut>2025-07-26T00:00:00</checkOut>
        <amount>800000.0</amount>
        <submittedAt>2025-07-18T18:47:42</submittedAt>
        <status>Đã bị hủy</status>
        <Person/>
        <History>
            <timestamp>2025-07-18T18:47:03</timestamp>
            <status>Gửi yêu cầu</status>
        </History>
        <History>
            <timestamp>2025-07-18T18:47:15</timestamp>
            <status>Đã được duyệt</status>
        </History>
        <History>
            <timestamp>2025-07-18T18:47:27</timestamp>
            <status>Gửi yêu cầu hủy</status>
        </History>
        <History>
            <timestamp>2025-07-18T18:47:42</timestamp>
            <status>Đã bị hủy</status>
        </History>
    </Request>
    <Request>
        <requestId>REQDE741</requestId>
        <userName>husky123</userName>
        <fullName>Trinh Nhu Nhat</fullName>
        <email>asd23@gmail.com</email>
        <phone>0999999999</phone>
        <roomId>R017</roomId>
        <checkIn>2025-07-19T00:00:00</checkIn>
        <checkOut>2025-07-26T00:00:00</checkOut>
        <amount>800000.0</amount>
        <submittedAt>2025-07-18T18:46:25</submittedAt>
        <status>Đã bị hủy</status>
        <Person/>
        <History>
            <timestamp>2025-07-18T18:45:18</timestamp>
            <status>Gửi yêu cầu</status>
        </History>
        <History>
            <timestamp>2025-07-18T18:45:47</timestamp>
            <status>Đã đọc</status>
        </History>
        <History>
            <timestamp>2025-07-18T18:45:55</timestamp>
            <status>Đã được duyệt</status>
        </History>
        <History>
            <timestamp>2025-07-18T18:46:12</timestamp>
            <status>Gửi yêu cầu hủy</status>
        </History>
        <History>
            <timestamp>2025-07-18T18:46:25</timestamp>
            <status>Đã bị hủy</status>
        </History>
    </Request>
    <Request>
        <requestId>REQ43BAF</requestId>
        <userName>husky123</userName>
        <fullName>Trinh Nhu Nhat</fullName>
        <email>asd23@gmail.com</email>
        <phone>0999999999</phone>
        <roomId>R017</roomId>
        <checkIn>2025-07-19T06:00:00</checkIn>
        <checkOut>2025-07-24T10:00:00</checkOut>
        <amount>800000.0</amount>
        <submittedAt>2025-07-18T18:41:45</submittedAt>
        <status>Đã bị hủy</status>
        <Person/>
        <History>
            <timestamp>2025-07-18T18:39:52</timestamp>
            <status>Gửi yêu cầu</status>
        </History>
        <History>
            <timestamp>2025-07-18T18:40:42</timestamp>
            <status>Đã đọc</status>
        </History>
        <History>
            <timestamp>2025-07-18T18:40:48</timestamp>
            <status>Đã được duyệt</status>
        </History>
        <History>
            <timestamp>2025-07-18T18:41:07</timestamp>
            <status>Gửi yêu cầu hủy</status>
        </History>
        <History>
            <timestamp>2025-07-18T18:41:45</timestamp>
            <status>Đã bị hủy</status>
        </History>
    </Request>
    <Request>
        <requestId>REQB8034</requestId>
        <userName>husky123</userName>
        <fullName>Trinh Nhu Nhat</fullName>
        <email>asd23@gmail.com</email>
        <phone>0999999999</phone>
        <roomId>R017</roomId>
        <checkIn>2025-07-19T10:00:00</checkIn>
        <checkOut>2025-07-26T10:00:00</checkOut>
        <amount>800000.0</amount>
        <submittedAt>2025-07-18T18:40:14</submittedAt>
        <status>Đã bị hủy</status>
        <Person/>
        <History>
            <timestamp>2025-07-18T14:07:48</timestamp>
            <status>Gửi yêu cầu</status>
        </History>
        <History>
            <timestamp>2025-07-18T14:08:04</timestamp>
            <status>Đã được duyệt</status>
        </History>
        <History>
            <timestamp>2025-07-18T14:08:21</timestamp>
            <status>Gửi yêu cầu hủy</status>
        </History>
        <History>
            <timestamp>2025-07-18T14:08:34</timestamp>
            <status>Đã bị hủy</status>
        </History>
        <History>
            <timestamp>2025-07-18T18:38:45</timestamp>
            <status>Gửi yêu cầu hủy</status>
        </History>
        <History>
            <timestamp>2025-07-18T18:40:14</timestamp>
            <status>Đã bị hủy</status>
        </History>
    </Request>
    <Request>
        <requestId>REQABF6F</requestId>
        <userName>husky123</userName>
        <fullName>Trinh Nhu Nhat</fullName>
        <email>asd23@gmail.com</email>
        <phone>0999999999</phone>
        <roomId>R018</roomId>
        <checkIn>2025-07-19T10:00:00</checkIn>
        <checkOut>2025-07-26T12:00:00</checkOut>
        <amount>800000.0</amount>
        <submittedAt>2025-07-18T14:06:38</submittedAt>
        <status>Đã bị hủy</status>
        <Person/>
        <History>
            <timestamp>2025-07-18T14:04:38</timestamp>
            <status>Gửi yêu cầu</status>
        </History>
        <History>
            <timestamp>2025-07-18T14:05:15</timestamp>
            <status>Đã đọc</status>
        </History>
        <History>
            <timestamp>2025-07-18T14:05:19</timestamp>
            <status>Đã được duyệt</status>
        </History>
        <History>
            <timestamp>2025-07-18T14:06:21</timestamp>
            <status>Gửi yêu cầu hủy</status>
        </History>
        <History>
            <timestamp>2025-07-18T14:06:35</timestamp>
            <status>Đã đọc</status>
        </History>
        <History>
            <timestamp>2025-07-18T14:06:38</timestamp>
            <status>Đã bị hủy</status>
        </History>
    </Request>
    <Request>
        <requestId>REQA8D40</requestId>
        <userName>husky123</userName>
        <fullName>Trinh Nhu Nhat</fullName>
        <email>asd23@gmail.com</email>
        <phone>0999999999</phone>
        <roomId>R018</roomId>
        <checkIn>2025-07-19T10:00:00</checkIn>
        <checkOut>2025-07-26T10:00:00</checkOut>
        <amount>800000.0</amount>
        <submittedAt>2025-07-18T14:03:36</submittedAt>
        <status>Đã bị hủy</status>
        <Person/>
        <History>
            <timestamp>2025-07-18T14:03:03</timestamp>
            <status>Gửi yêu cầu</status>
        </History>
        <History>
            <timestamp>2025-07-18T14:03:31</timestamp>
            <status>Đã đọc</status>
        </History>
        <History>
            <timestamp>2025-07-18T14:03:36</timestamp>
            <status>Đã bị hủy</status>
        </History>
    </Request>
    <Request>
        <requestId>REQ7A011</requestId>
        <userName>husky123</userName>
        <fullName>Trinh Nhu Nhat</fullName>
        <email>asd23@gmail.com</email>
        <phone>0999999999</phone>
        <roomId>R018</roomId>
        <checkIn>2025-07-19T10:00:00</checkIn>
        <checkOut>2025-07-26T12:00:00</checkOut>
        <amount>800000.0</amount>
        <submittedAt>2025-07-18T14:02:04</submittedAt>
        <status>Đã từ chối</status>
        <Person/>
        <History>
            <timestamp>2025-07-18T14:00:35</timestamp>
            <status>Gửi yêu cầu</status>
        </History>
        <History>
            <timestamp>2025-07-18T14:01:43</timestamp>
            <status>Đã đọc</status>
        </History>
        <History>
            <timestamp>2025-07-18T14:02:04</timestamp>
            <status>Đã từ chối</status>
        </History>
    </Request>
    <Request>
        <requestId>REQC834B</requestId>
        <userName>husky123</userName>
        <fullName>Trinh Nhu Nhat</fullName>
        <email>asd23@gmail.com</email>
        <phone>0999999999</phone>
        <roomId>R018</roomId>
        <checkIn>2025-07-19T11:00:00</checkIn>
        <checkOut>2025-07-26T13:00:00</checkOut>
        <amount>800000.0</amount>
        <submittedAt>2025-07-18T13:51:49</submittedAt>
        <status>Đã bị hủy</status>
        <Person/>
        <History>
            <timestamp>2025-07-18T13:50:46</timestamp>
            <status>Gửi yêu cầu</status>
        </History>
        <History>
            <timestamp>2025-07-18T13:51:14</timestamp>
            <status>Đã được duyệt</status>
        </History>
        <History>
            <timestamp>2025-07-18T13:51:34</timestamp>
            <status>Gửi yêu cầu hủy</status>
        </History>
        <History>
            <timestamp>2025-07-18T13:51:49</timestamp>
            <status>Đã bị hủy</status>
        </History>
    </Request>
    <Request>
        <requestId>REQ705AD</requestId>
        <userName>husky123</userName>
        <fullName>Trinh Nhu Nhat</fullName>
        <email>asd23@gmail.com</email>
        <phone>0999999999</phone>
        <roomId>R019</roomId>
        <checkIn>2025-07-19T10:00:00</checkIn>
        <checkOut>2025-07-26T13:00:00</checkOut>
        <amount>800000.0</amount>
        <submittedAt>2025-07-18T13:49:31</submittedAt>
        <status>Đã bị hủy</status>
        <Person/>
        <History>
            <timestamp>2025-07-18T13:47:49</timestamp>
            <status>Gửi yêu cầu</status>
        </History>
        <History>
            <timestamp>2025-07-18T13:48:16</timestamp>
            <status>Đã đọc</status>
        </History>
        <History>
            <timestamp>2025-07-18T13:48:20</timestamp>
            <status>Đã được duyệt</status>
        </History>
        <History>
            <timestamp>2025-07-18T13:49:09</timestamp>
            <status>Gửi yêu cầu hủy</status>
        </History>
        <History>
            <timestamp>2025-07-18T13:49:31</timestamp>
            <status>Đã bị hủy</status>
        </History>
    </Request>
    <Request>
        <requestId>REQ1B0BB</requestId>
        <userName>husky123</userName>
        <fullName>Trinh Nhu Nhat</fullName>
        <email>asd23@gmail.com</email>
        <phone>0999999999</phone>
        <roomId>R019</roomId>
        <checkIn>2025-07-19T09:00:00</checkIn>
        <checkOut>2025-07-25T09:00:00</checkOut>
        <amount>800000.0</amount>
        <submittedAt>2025-07-18T13:46:58</submittedAt>
        <status>Đã bị hủy</status>
        <Person/>
        <History>
            <timestamp>2025-07-18T13:46:01</timestamp>
            <status>Gửi yêu cầu</status>
        </History>
        <History>
            <timestamp>2025-07-18T13:46:33</timestamp>
            <status>Đã đọc</status>
        </History>
        <History>
            <timestamp>2025-07-18T13:46:58</timestamp>
            <status>Đã bị hủy</status>
        </History>
    </Request>
    <Request>
        <requestId>REQ40272</requestId>
        <userName>husky123</userName>
        <fullName>Trinh Nhu Nhat</fullName>
        <email>asd23@gmail.com</email>
        <phone>0999999999</phone>
        <roomId>R019</roomId>
        <checkIn>2025-07-19T10:00:00</checkIn>
        <checkOut>2025-07-21T10:00:00</checkOut>
        <amount>800000.0</amount>
        <submittedAt>2025-07-18T13:45:09</submittedAt>
        <status>Đã từ chối</status>
        <Person/>
        <History>
            <timestamp>2025-07-18T13:43:31</timestamp>
            <status>Gửi yêu cầu</status>
        </History>
        <History>
            <timestamp>2025-07-18T13:44:14</timestamp>
            <status>Đã đọc</status>
        </History>
        <History>
            <timestamp>2025-07-18T13:45:09</timestamp>
            <status>Đã từ chối</status>
        </History>
    </Request>
    <Request>
        <requestId>REQ7EAA2</requestId>
        <userName>husky123</userName>
        <fullName>Trinh Nhu Nhat</fullName>
        <email>asd23@gmail.com</email>
        <phone>0999999999</phone>
        <roomId>R019</roomId>
        <checkIn>2025-07-19T10:00:00</checkIn>
        <checkOut>2025-07-26T10:00:00</checkOut>
        <amount>800000.0</amount>
        <submittedAt>2025-07-18T13:42:06</submittedAt>
        <status>Đã từ chối</status>
        <Person/>
        <History>
            <timestamp>2025-07-18T13:40:46</timestamp>
            <status>Gửi yêu cầu</status>
        </History>
        <History>
            <timestamp>2025-07-18T13:42:06</timestamp>
            <status>Đã từ chối</status>
        </History>
    </Request>
</Requests>
